dputils/i2e/__init__.py
dputils/i2e/__main__.py
dputils/i2e/edb.py
dputils/i2e/get_failed.py
dputils/i2e/internal_to_external.py
dputils/i2e/log.py
dputils/i2e/pg.py
dputils/i2e/req.py
dputils/i2e/structs.py
dputils_i2e-1.0.0.dist-info/METADATA
dputils_i2e-1.0.0.dist-info/WHEEL
dputils_i2e-1.0.0.dist-info/entry_points.txt
dputils_i2e-1.0.0.dist-info/top_level.txt
dputils_i2e-1.0.0.dist-info/RECORD
